nlp_text_search/__init__.py
nlp_text_search/custom_vp_tree.py
nlp_text_search/dists.py
nlp_text_search/helpers.py
nlp_text_search/search_engine.py
nlp_text_search/settings.py
nlp_text_search/vp_tree.py
nlp_text_search-0.4.dist-info/LICENSE
nlp_text_search-0.4.dist-info/METADATA
nlp_text_search-0.4.dist-info/WHEEL
nlp_text_search-0.4.dist-info/top_level.txt
nlp_text_search-0.4.dist-info/RECORD
