Metadata-Version: 2.1
Name: nlp-text-search
Version: 0.4
Summary: Fulltext-like search using NLP concept
Home-page: https://github.com/basalovyurij/nlp-text-search
Author: Yurij Basalov
Author-email: basalov_yurij@mail.ru
License: UNKNOWN
Platform: UNKNOWN
Classifier: Programming Language :: Python :: 3
Classifier: License :: OSI Approved :: MIT License
Classifier: Operating System :: OS Independent
Requires-Python: >=3.6
